{
  "version": "0.0.9",
  "description": "A Snap for making transactions on the Iota blockchain",
  "proposedName": "Iota",
  "repository": {
    "type": "git",
    "url": "git+https://github.com/Liquidlink-Lab/iota-metamask-snap.git"
  },
  "source": {
    "shasum": "3GejL5Vk9CBYFvj8HDZUl/vuBRhzYmbe9EukR69ZzwY=",
    "location": {
      "npm": {
        "filePath": "dist/bundle.js",
        "iconPath": "images/icon.svg",
        "packageName": "@liquidlink-lab/iota-metamask-snap",
        "registry": "https://registry.npmjs.org/"
      }
    }
  },
  "initialPermissions": {
    "snap_dialog": {},
    "endowment:rpc": {
      "dapps": true,
      "snaps": false
    },
    "endowment:network-access": {},
    "snap_getBip32Entropy": [
      {
        "path": ["m", "44'", "4218'"],
        "curve": "ed25519"
      }
    ],
    "snap_manageState": {}
  },
  "platformVersion": "6.22.0",
  "manifestVersion": "0.1"
}
